<?xml version="1.0" encoding="UTF-8"?>
<!-- data for each bot here -->

<bots>
	<mybotpath>C:\MyBot-MBR_v7.5\</mybotpath>
	
	<bot>
		<key>1</key>
		<profile>whodat</profile>
		<memuInstance>MEmu_1</memuInstance>
	</bot>
	<bot>
		<key>2</key>
		<profile>wedey</profile>
		<memuInstance>MEmu_2</memuInstance>
	</bot>
	<bot>
		<key>3</key>
		<profile>Believedat</profile>
		<memuInstance>MEmu_3</memuInstance>
	</bot>
	<bot>
		<key>4</key>
		<profile>Orz</profile>
		<memuInstance>MEmu_4</memuInstance>
	</bot>
	<bot>
		<key>5</key>
		<profile>DemSaints</profile>
		<memuInstance>MEmu_5</memuInstance>
	</bot>
	<bot>
		<key>6</key>
		<profile>ElBlanco</profile>
		<memuInstance>MEmu_6</memuInstance>
	</bot>
	<bot>
		<key>7</key>
		<profile>yehat</profile>
		<memuInstance>MEmu_7</memuInstance>
	</bot>
</bots>